hpc/__init__.py
hpc/base/__init__.py
hpc/base/core.py
hpc/base/type.py
hpc/compat/__init__.py
hpc/compat/functools.py
hpc/impl/_.py
hpc/impl/__init__.py
hpc/impl/remote_path.py
hpc/impl/server.py
hpc/mngr/__init__.py
hpc/mngr/lsf/__init__.py
hpc/mngr/lsf/core.py
hpc/mngr/lsf/extra/__init__.py
hpc/mngr/lsf/extra/command.py
hpc/mngr/lsf/extra/job.py
hpc/namespace.py
ihpc-0.1.2.dist-info/LICENSE.txt
ihpc-0.1.2.dist-info/WHEEL
ihpc-0.1.2.dist-info/METADATA
ihpc-0.1.2.dist-info/RECORD
